{
  "_meta": {
    "description": "Carrier rates from Christchurch warehouse. Mainfreight = flat per-destination. Dailyfreight = zone-subdivided per-hub with volume-tier discounts.",
    "updated": "2026-05-28",
    "origin": "7 Paradyne Place, Wigram, Christchurch 8042"
  },
  "castle_parcels": {
    "_meta": {
      "label":   "Castle Parcels (Post Haste)",
      "rep":     "Antonya Hector — Antonya.hector@posthaste.co.nz — 027 209 3528",
      "vintage": "Valid until July 2026",
      "note":    "Live quotes via GoSweetSpot API in production. Table here is reference only. Per-parcel pricing — no volume discount."
    },
    "brackets": [
      {"cube_m3": 0.015, "max_kg": 25},
      {"cube_m3": 0.030, "max_kg": 25},
      {"cube_m3": 0.050, "max_kg": 25},
      {"cube_m3": 0.075, "max_kg": 25},
      {"cube_m3": 0.100, "max_kg": 25},
      {"cube_m3": 0.125, "max_kg": 25},
      {"cube_m3": 0.135, "max_kg": 25},
      {"cube_m3": 0.160, "max_kg": 25}
    ],
    "zones": [
      {"id": "chch_local",   "name": "Local (ChCh Metro)",                  "rates": [3.97, 3.97, 3.97, 3.97, 3.97, 3.97, 3.97, 3.97]},
      {"id": "chch_outer",   "name": "Outer (Outside Metro)",               "rates": [4.80, 4.80, 4.80, 4.80, 4.80, 4.80, 4.80, 4.80]},
      {"id": "regional_si",  "name": "Regional (Kaikoura, Timaru)",         "rates": [4.80, 5.55, 6.56, 7.81, 9.06, 10.31, 10.82, 22.51]},
      {"id": "within_si",    "name": "Within Island (Nelson, Dunedin)",     "rates": [5.94, 7.84, 10.37, 13.52, 16.68, 19.85, 21.11, 34.70]},
      {"id": "ni_upper",     "name": "NI 2-Day Upper (Auckland, Hamilton)", "rates": [6.43, 8.81, 11.99, 15.95, 19.92, 23.89, 25.47, 39.89]},
      {"id": "ni_lower",     "name": "NI 2-Day Lower (Wellington)",         "rates": [5.74, 8.67, 10.44, 14.62, 19.63, 24.53, 27.14, 39.89]}
    ],
    "surcharges": {
      "rural_delivery":       7.09,
      "residential_delivery": 2.53
    }
  },
  "mainfreight": {
    "_meta": {
      "label":   "Mainfreight",
      "service": "M2H Two-Man Delivery",
      "vintage": "Current rate card",
      "formula": "MAX(min_charge, base + per_m³ × cart_CBM) × FAF (1.30) × GST (1.15)",
      "note":    "Flat per-destination rate (no zone subdivision). Use for heavy items / two-man delivery."
    },
    "rates": {
      "auckland":         {"base": 33, "min": 50, "per_m3": 71.74},
      "blenheim":         {"base": 30, "min": 37, "per_m3": 53.56},
      "christchurch":     {"base": 30, "min": 27, "per_m3": 16.48},
      "cromwell":         {"base": 33, "min": 40, "per_m3": 59.96},
      "dunedin":          {"base": 30, "min": 37, "per_m3": 51.50},
      "gisborne":         {"base": 33, "min": 50, "per_m3": 137.05},
      "greymouth":        {"base": 30, "min": 37, "per_m3": 70.04},
      "hamilton":         {"base": 33, "min": 50, "per_m3": 91.01},
      "invercargill":     {"base": 30, "min": 37, "per_m3": 52.53},
      "kaitaia":          {"base": 33, "min": 50, "per_m3": 141.33},
      "levin":            {"base": 33, "min": 50, "per_m3": 70.67},
      "napier":           {"base": 33, "min": 50, "per_m3": 134.91},
      "nelson":           {"base": 30, "min": 37, "per_m3": 53.56},
      "new plymouth":     {"base": 33, "min": 50, "per_m3": 130.62},
      "oamaru":           {"base": 30, "min": 47, "per_m3": 61.80},
      "palmerston north": {"base": 33, "min": 50, "per_m3": 70.67},
      "rotorua":          {"base": 33, "min": 50, "per_m3": 113.49},
      "taupo":            {"base": 33, "min": 50, "per_m3": 117.78},
      "tauranga":         {"base": 33, "min": 50, "per_m3": 91.01},
      "thames":           {"base": 33, "min": 50, "per_m3": 106.00},
      "timaru":           {"base": 30, "min": 47, "per_m3": 43.26},
      "wanganui":         {"base": 33, "min": 50, "per_m3": 137.05},
      "wellington":       {"base": 33, "min": 50, "per_m3": 65.31},
      "whangarei":        {"base": 33, "min": 50, "per_m3": 132.76}
    }
  },
  "dailyfreight": {
    "_meta": {
      "label":   "Dailyfreight",
      "service": "LCL (Less than Container Load) Palletised",
      "vintage": "April 2026 rates",
      "formula": "MAX(base, per_m3_tier × cart_CBM) × FAF (1.30) × GST (1.15)",
      "tiers":   "Per-m³ rate drops with cart size: tier 0 = <5m³, tier 1 = 5-9.99m³, tier 2 = ≥10m³",
      "note":    "Hub-and-spoke zones: zone 1-2 = metro hub city only; higher zones = outlying towns. Use a city alias to route to the right zone."
    },
    "rates": {
      "ashburton":          {"base": 39, "tiers": [32, 30, 28]},
      "auckland_z1":        {"base": 51, "tiers": [75.88, 73.61, 72.12]},
      "auckland_z3":        {"base": 53, "tiers": [84.20, 80.30, 78.21]},
      "auckland_z9":        {"base": 57, "tiers": [107.24, 105.24, 103.24]},
      "blenheim":           {"base": 39, "tiers": [62, 60, 58]},
      "christchurch":       {"base": 29, "tiers": [25, 25, 25]},
      "cromwell_z1":        {"base": 42, "tiers": [67.57, 65.57, 65.57]},
      "cromwell_z5":        {"base": 47, "tiers": [90.44, 88.44, 86.44]},
      "dunedin":            {"base": 39, "tiers": [61, 59, 57]},
      "gore":               {"base": 48, "tiers": [70, 68, 66]},
      "greymouth":          {"base": 39, "tiers": [54, 52, 50]},
      "hamilton_z1":        {"base": 51, "tiers": [88.36, 86.36, 84.36]},
      "hamilton_z3":        {"base": 53, "tiers": [101.24, 99.24, 97.24]},
      "hamilton_z10":       {"base": 57, "tiers": [129.89, 127.89, 125.89]},
      "invercargill":       {"base": 39, "tiers": [67, 65, 63]},
      "kaitaia":            {"base": 57, "tiers": [218.30, 214.30, 210.30]},
      "levin":              {"base": 51, "tiers": [72.77, 70.77, 68.77]},
      "masterton":          {"base": 51, "tiers": [116.42, 114.42, 112.42]},
      "napier":             {"base": 51, "tiers": [132.02, 130.02, 128.02]},
      "nelson":             {"base": 39, "tiers": [54, 52, 50]},
      "new plymouth":       {"base": 51, "tiers": [127.86, 125.86, 123.86]},
      "oamaru":             {"base": 39, "tiers": [60, 58, 56]},
      "palmerston north":   {"base": 51, "tiers": [71.73, 69.73, 67.73]},
      "rotorua":            {"base": 51, "tiers": [110.19, 108.19, 106.19]},
      "taupo":              {"base": 51, "tiers": [114.35, 112.35, 110.35]},
      "tauranga":           {"base": 51, "tiers": [88.36, 86.36, 84.36]},
      "thames":             {"base": 51, "tiers": [103.95, 101.95, 99.95]},
      "timaru":              {"base": 39, "tiers": [40, 38, 36]},
      "wanganui":           {"base": 51, "tiers": [135.14, 133.14, 131.14]},
      "wellington":         {"base": 48, "tiers": [65.49, 63.49, 61.49]},
      "whakatane":          {"base": 51, "tiers": [124.74, 122.74, 120.74]},
      "whangarei":          {"base": 51, "tiers": [145.53, 143.53, 141.53]}
    }
  },
  "city_aliases": {
    "_note": "Maps customer city/suburb to a Dailyfreight rate key. Use 'city_zN' for hubs with multiple zones; bare city for single-zone destinations.",
    "lower hutt": "wellington",
    "upper hutt": "wellington",
    "porirua": "wellington",
    "petone": "wellington",
    "paraparaumu": "wellington",
    "kapiti": "wellington",
    "auckland": "auckland_z1",
    "auckland central": "auckland_z1",
    "manukau": "auckland_z1",
    "north shore": "auckland_z1",
    "henderson": "auckland_z1",
    "takapuna": "auckland_z1",
    "papakura": "auckland_z1",
    "albany": "auckland_z1",
    "botany": "auckland_z1",
    "waitakere": "auckland_z1",
    "browns bay": "auckland_z1",
    "birkenhead": "auckland_z1",
    "glenfield": "auckland_z1",
    "devonport": "auckland_z1",
    "mt eden": "auckland_z1",
    "mount eden": "auckland_z1",
    "ponsonby": "auckland_z1",
    "parnell": "auckland_z1",
    "newmarket": "auckland_z1",
    "remuera": "auckland_z1",
    "epsom": "auckland_z1",
    "mt albert": "auckland_z1",
    "mount albert": "auckland_z1",
    "ellerslie": "auckland_z1",
    "panmure": "auckland_z1",
    "otahuhu": "auckland_z1",
    "manurewa": "auckland_z1",
    "mangere": "auckland_z1",
    "mangere bridge": "auckland_z1",
    "onehunga": "auckland_z1",
    "pakuranga": "auckland_z1",
    "howick": "auckland_z1",
    "east tamaki": "auckland_z1",
    "new lynn": "auckland_z1",
    "avondale": "auckland_z1",
    "te atatu": "auckland_z1",
    "glen eden": "auckland_z1",
    "pukekohe": "auckland_z3",
    "waiuku": "auckland_z3",
    "bombay": "auckland_z3",
    "drury": "auckland_z3",
    "karaka": "auckland_z3",
    "patumahoe": "auckland_z3",
    "tuakau": "auckland_z3",
    "pokeno": "auckland_z3",
    "helensville": "auckland_z3",
    "kumeu": "auckland_z3",
    "riverhead": "auckland_z3",
    "coatesville": "auckland_z3",
    "dairy flat": "auckland_z3",
    "warkworth": "auckland_z3",
    "wellsford": "auckland_z3",
    "snells beach": "auckland_z3",
    "matakana": "auckland_z3",
    "leigh": "auckland_z3",
    "beachlands": "auckland_z3",
    "maraetai": "auckland_z3",
    "clevedon": "auckland_z3",
    "hunua": "auckland_z3",
    "whitford": "auckland_z3",
    "waiheke": "auckland_z9",
    "waiheke island": "auckland_z9",
    "great barrier": "auckland_z9",
    "great barrier island": "auckland_z9",
    "ostend": "auckland_z9",
    "oneroa": "auckland_z9",
    "onetangi": "auckland_z9",
    "rolleston": "christchurch",
    "lincoln": "christchurch",
    "rangiora": "christchurch",
    "prebbleton": "christchurch",
    "halswell": "christchurch",
    "darfield": "christchurch",
    "oxford": "christchurch",
    "amberley": "christchurch",
    "kaiapoi": "christchurch",
    "lyttelton": "christchurch",
    "sumner": "christchurch",
    "wigram": "christchurch",
    "burnside": "christchurch",
    "kerikeri": "whangarei",
    "paihia": "whangarei",
    "dargaville": "whangarei",
    "kawakawa": "whangarei",
    "russell": "whangarei",
    "kaikohe": "whangarei",
    "kaikoura": "blenheim",
    "cromwell": "cromwell_z1",
    "queenstown": "cromwell_z5",
    "wanaka": "cromwell_z5",
    "lake hawea": "cromwell_z5",
    "hawea": "cromwell_z5",
    "cardrona": "cromwell_z5",
    "arrowtown": "cromwell_z5",
    "glenorchy": "cromwell_z5",
    "kingston": "cromwell_z5",
    "frankton": "cromwell_z5",
    "alexandra": "cromwell_z5",
    "clyde": "cromwell_z5",
    "bannockburn": "cromwell_z5",
    "tarras": "cromwell_z5",
    "roxburgh": "cromwell_z5",
    "lawrence": "cromwell_z5",
    "lake wakatipu": "cromwell_z5",
    "lake wanaka": "cromwell_z5",
    "richmond": "nelson",
    "motueka": "nelson",
    "westport": "greymouth",
    "hokitika": "greymouth",
    "hawera": "wanganui",
    "stratford": "new plymouth",
    "inglewood": "new plymouth",
    "hamilton": "hamilton_z1",
    "hamilton central": "hamilton_z1",
    "hamilton east": "hamilton_z1",
    "hillcrest": "hamilton_z1",
    "chartwell": "hamilton_z1",
    "rototuna": "hamilton_z1",
    "dinsdale": "hamilton_z1",
    "te awamutu": "hamilton_z3",
    "cambridge": "hamilton_z3",
    "morrinsville": "hamilton_z3",
    "matamata": "hamilton_z3",
    "huntly": "hamilton_z3",
    "ngaruawahia": "hamilton_z3",
    "te kauwhata": "hamilton_z3",
    "pirongia": "hamilton_z3",
    "tirau": "hamilton_z3",
    "putaruru": "hamilton_z3",
    "otorohanga": "hamilton_z3",
    "tokoroa": "hamilton_z3",
    "te kuiti": "hamilton_z10",
    "kawhia": "hamilton_z10",
    "taumarunui": "hamilton_z10",
    "pio pio": "hamilton_z10",
    "raglan": "hamilton_z10",
    "mount maunganui": "tauranga",
    "te puke": "tauranga",
    "katikati": "tauranga",
    "papamoa": "tauranga",
    "omokoroa": "tauranga",
    "opotiki": "whakatane",
    "feilding": "palmerston north",
    "dannevirke": "palmerston north",
    "pahiatua": "palmerston north",
    "wairoa": "napier",
    "hastings": "napier",
    "waipukurau": "napier",
    "paeroa": "thames",
    "geraldine": "timaru",
    "methven": "ashburton",
    "balclutha": "dunedin",
    "milton": "dunedin",
    "mosgiel": "dunedin"
  }
}
